pypermacc/__init__.py
pypermacc/api.py
pypermacc-0.1.1.dist-info/LICENSE
pypermacc-0.1.1.dist-info/METADATA
pypermacc-0.1.1.dist-info/WHEEL
pypermacc-0.1.1.dist-info/top_level.txt
pypermacc-0.1.1.dist-info/RECORD
